climax/__init__.py
climax/__main__.py
climax/config.py
climax/eggs.py
climax/gui.py
climax/max_releases.json
climax/model.py
climax/locales/en/LC_MESSAGES/messages.mo
climax/locales/en/LC_MESSAGES/messages.po
climax/locales/fr/LC_MESSAGES/messages.mo
climax/locales/fr/LC_MESSAGES/messages.po
climax_certic-0.2.12.dist-info/METADATA
climax_certic-0.2.12.dist-info/WHEEL
climax_certic-0.2.12.dist-info/entry_points.txt
climax_certic-0.2.12.dist-info/licenses/LICENSE
climax_certic-0.2.12.dist-info/RECORD
