Metadata-Version: 2.4
Name: climax-CERTIC
Version: 0.2.12
Summary: CLI tool for MaX, Le Moteur d'Affichage XML.
Author-email: Mickaël Desfrênes <mickael.desfrenes@unicaen.fr>
Maintainer-email: Mickaël Desfrênes <mickael.desfrenes@unicaen.fr>
License: CECILL-C
License-File: LICENSE
Requires-Python: >=3.9
Requires-Dist: basexclient>=8.4.4
Requires-Dist: beautifulsoup4>=4.12.3
Requires-Dist: bottle>=0.13.2
Requires-Dist: geler-certic>=0.4.4
Requires-Dist: lxml-html-clean>=0.4.1
Requires-Dist: lxml>=5.3.0
Requires-Dist: oora>=0.2.6
Requires-Dist: pyinstaller>=6.11.1
Requires-Dist: requests>=2.32.3
Requires-Dist: simple-term-menu>=1.6.6
Requires-Dist: typer>=0.15.1
